eb_ssm/__init__.py
eb_ssm/eb_ssm.py
eb_ssm-1.3.0.dist-info/licenses/LICENSE
eb_ssm-1.3.0.dist-info/METADATA
eb_ssm-1.3.0.dist-info/WHEEL
eb_ssm-1.3.0.dist-info/entry_points.txt
eb_ssm-1.3.0.dist-info/top_level.txt
eb_ssm-1.3.0.dist-info/RECORD
