Metadata-Version: 2.4
Name: eb-ssm
Version: 1.3.0
Summary: Simple tool to SSH into an Elastic Beanstalk server using AWS SSM.
Author: Inc.
Author-email: Zagaran <info@zagaran.com>
License-Expression: MIT
Project-URL: Homepage, https://github.com/zagaran/eb-ssm
Keywords: aws,eb,ssm,elastic,beanstalk,systems,manager,agent,ssh
Classifier: Programming Language :: Python :: 3
Classifier: Operating System :: OS Independent
Requires-Python: >=3.6
License-File: LICENSE
Requires-Dist: awsebcli>=3.14.0
Dynamic: license-file
